LICENSE
README.md
setup.py
braid_mrf.egg-info/PKG-INFO
braid_mrf.egg-info/SOURCES.txt
braid_mrf.egg-info/dependency_links.txt
braid_mrf.egg-info/top_level.txt
braidmrf/__init__.py
braidmrf/__main__.py
braidmrf/inputFile/__init__.py
braidmrf/inputFile/inputBioplex.py
braidmrf/inputFile/inputFile.py
braidmrf/meanfield/__init__.py
braidmrf/meanfield/fast_matmul.py
braidmrf/meanfield/simulateLikelihood.py
braidmrf/observation/__init__.py
braidmrf/observation/countBioplexSpokeModel.py
braidmrf/observation/countSpokeModel.py